dielectric/__init__.py
dielectric/constants.py
dielectric/classes/__init__.py
dielectric/classes/cells.py
dielectric/classes/colloids.py
dielectric/classes/electrolytes.py
dielectric/classes/particles.py
dielectric/ivp/__init__.py
dielectric/ivp/burst.py
dielectric/ivp/envelope.py
dielectric/ivp/furukawa.py
dielectric/ivp/ivptools.py
dielectric/ivp/k_wave.py
dielectric/ivp/peaks.py
dielectric/ivp/pydsr_examples.py
dielectric/ivp/salve.py
dielectric/ivp/signal.py
dielectric/ivp/stride.py
dielectric/ivp/tom.py
dielectric/models/__init__.py
dielectric/models/cell_models.py
dielectric/poly/__init__.py
dielectric/poly/polyplot.py
dielectric/poly/polyutils.py
dielectric/utils/__init__.py
dielectric/utils/file_utils.py
dielectric/utils/hp4194.py
dielectric/utils/openshortload.py
dielectric-2.0.4.dist-info/licenses/LICENSE
dielectric-2.0.4.dist-info/METADATA
dielectric-2.0.4.dist-info/WHEEL
dielectric-2.0.4.dist-info/top_level.txt
dielectric-2.0.4.dist-info/RECORD
