Metadata-Version: 2.4
Name: dielectric
Version: 2.0.4
Summary: Dielectric Spectroscopy analysis software in Python
Author-email: "Paul J.M. van Kan" <pjm@vankanscientific.nl>
Project-URL: Homepage, https://bitbucket.org/deltares/dielectric/
Classifier: Programming Language :: Python :: 3
Classifier: License :: OSI Approved :: GNU General Public License v3 or later (GPLv3+)
Classifier: Operating System :: OS Independent
Requires-Python: >=3.11
License-File: LICENSE
Dynamic: license-file
